betdaq_wng/__init__.py
betdaq_wng/apiclient.py
betdaq_wng/baseclient.py
betdaq_wng/classifiers/__init__.py
betdaq_wng/classifiers/betting.py
betdaq_wng/classifiers/marketdata.py
betdaq_wng/compat.py
betdaq_wng/endpoints/__init__.py
betdaq_wng/endpoints/account.py
betdaq_wng/endpoints/baseendpoint.py
betdaq_wng/endpoints/betting.py
betdaq_wng/endpoints/marketdata.py
betdaq_wng/endpoints/trading.py
betdaq_wng/enums.py
betdaq_wng/errorparsers/__init__.py
betdaq_wng/errorparsers/betting.py
betdaq_wng/errorparsers/marketdata.py
betdaq_wng/exceptions.py
betdaq_wng/filters.py
betdaq_wng/resources/__init__.py
betdaq_wng/resources/accountresources.py
betdaq_wng/resources/baseresources.py
betdaq_wng/resources/bettingresources.py
betdaq_wng/resources/marketdataresources.py
betdaq_wng/resources/tradingresources.py
betdaq_wng/utils.py
betdaq_wng-0.0.16.dist-info/LICENSE
betdaq_wng-0.0.16.dist-info/METADATA
betdaq_wng-0.0.16.dist-info/WHEEL
betdaq_wng-0.0.16.dist-info/RECORD
