Metadata-Version: 2.1
Name: betdaq_wng
Version: 0.0.16
Summary: Betdaq API Python wrapper
License: MIT
Author: Rory Cole
Author-email: rory.cole1990@gmail.com
Maintainer: Luka Tavkhelidze
Maintainer-email: tavkhelidzeluka@gmail.com
Requires-Python: >=3.11,<=3.13
Classifier: License :: OSI Approved :: MIT License
Classifier: Programming Language :: Python :: 3
Classifier: Programming Language :: Python :: 3.11
Classifier: Programming Language :: Python :: 3.12
Requires-Dist: python-dateutil (>=2.8.2,<3.0.0)
Requires-Dist: requests (>=2.31.0,<3.0.0)
Requires-Dist: zeep (>=4.2.1,<5.0.0)
